reticulok/__init__.py
reticulok/leetcode/__init__.py
reticulok/leetcode/easy.py
reticulok/leetcode/medium.py
tests/__init__.py
tests/test_import.py
tests/test_leetcode/__init__.py
tests/test_leetcode/test_easy.py
tests/test_leetcode/test_medium.py
reticulok-0.0.9.dist-info/LICENSE
reticulok-0.0.9.dist-info/METADATA
reticulok-0.0.9.dist-info/WHEEL
reticulok-0.0.9.dist-info/top_level.txt
reticulok-0.0.9.dist-info/RECORD
