Metadata-Version: 2.1
Name: reticulok
Version: 0.0.9
Summary: Package that stores coding question answers
Home-page: UNKNOWN
Author: Michael Lok
License: GNU General Public License v3.0
Platform: UNKNOWN
License-File: LICENSE
Requires-Dist: requests
Requires-Dist: importlib-metadata ; python_version < "3.8"
